taskwait/__about__.py
taskwait/__init__.py
taskwait/py.typed
taskwait-0.1.2.dist-info/METADATA
taskwait-0.1.2.dist-info/WHEEL
taskwait-0.1.2.dist-info/licenses/LICENSE.txt
taskwait-0.1.2.dist-info/RECORD
