Metadata-Version: 2.4
Name: taskwait
Version: 0.1.2
Summary: Wait for a task to complete
Project-URL: Documentation, https://github.com/reside-ic/taskwait#readme
Project-URL: Issues, https://github.com/reside-ic/taskwait/issues
Project-URL: Source, https://github.com/reside-ic/taskwait
Author-email: Rich FitzJohn <r.fitzjohn@imperial.ac.uk>
License-Expression: MIT
License-File: LICENSE.txt
Classifier: Development Status :: 4 - Beta
Classifier: Programming Language :: Python
Classifier: Programming Language :: Python :: 3.8
Classifier: Programming Language :: Python :: 3.9
Classifier: Programming Language :: Python :: 3.10
Classifier: Programming Language :: Python :: 3.11
Classifier: Programming Language :: Python :: 3.12
Classifier: Programming Language :: Python :: Implementation :: CPython
Classifier: Programming Language :: Python :: Implementation :: PyPy
Requires-Python: >=3.8
